monaistream/__init__.py
monaistream/_version.py
monaistream/compose.py
monaistream/errors.py
monaistream/interface.py
monaistream/logging.json
monaistream/filters/__init__.py
monaistream/filters/convert.py
monaistream/filters/infer.py
monaistream/filters/transform.py
monaistream/filters/transform_cupy.py
monaistream/filters/util.py
monaistream/sinks/__init__.py
monaistream/sinks/fake.py
monaistream/sinks/nveglglessink.py
monaistream/sources/__init__.py
monaistream/sources/ajavideosrc.py
monaistream/sources/sourcebin.py
monaistream/sources/testvideosrc.py
monaistream/sources/uri.py
monaistream/util/__init__.py
monaistream/util/convert.py
monaistream/util/entry.py
monaistream-0.1.1.data/data/logconfig/logging.json
monaistream-0.1.1.dist-info/LICENSE
monaistream-0.1.1.dist-info/METADATA
monaistream-0.1.1.dist-info/WHEEL
monaistream-0.1.1.dist-info/entry_points.txt
monaistream-0.1.1.dist-info/top_level.txt
monaistream-0.1.1.dist-info/RECORD
