Metadata-Version: 2.1
Name: monaistream
Version: 0.1.1
Summary: Streaming Inference Extension for MONAI
Home-page: https://monai.io/
Author: MONAI Consortium
Author-email: monai.contact@gmail.com
License: Apache License 2.0
Project-URL: Documentation, https://docs.monai.io/
Project-URL: Bug Tracker, https://github.com/Project-MONAI/MONAIStream/issues
Project-URL: Source Code, https://github.com/Project-MONAI/MONAIStream
Platform: OS Independent
Requires-Python: >=3.6
Requires-Dist: monai[gdown,itk,pillow,psutil,skimage,torchvision] (==0.7.0)
